spark_dataproc_local_tools/__init__.py
spark_dataproc_local_tools/functions/__init__.py
spark_dataproc_local_tools/functions/generator.py
spark_dataproc_local_tools/utils/__init__.py
spark_dataproc_local_tools-0.1.4.dist-info/LICENSE
spark_dataproc_local_tools-0.1.4.dist-info/METADATA
spark_dataproc_local_tools-0.1.4.dist-info/WHEEL
spark_dataproc_local_tools-0.1.4.dist-info/top_level.txt
spark_dataproc_local_tools-0.1.4.dist-info/RECORD
